mps_carafe/_C.cpython-314-darwin.so
mps_carafe/__init__.py
mps_carafe/csrc/carafe_mps.mm
mps_carafe-0.1.4.dist-info/METADATA
mps_carafe-0.1.4.dist-info/WHEEL
mps_carafe-0.1.4.dist-info/top_level.txt
mps_carafe-0.1.4.dist-info/RECORD
